chaosfault/__init__.py
chaosfault/__version__.py
chaosfault/actions.py
chaostoolkit_fault-0.1.2.dist-info/METADATA
chaostoolkit_fault-0.1.2.dist-info/WHEEL
chaostoolkit_fault-0.1.2.dist-info/entry_points.txt
chaostoolkit_fault-0.1.2.dist-info/licenses/LICENSE
chaostoolkit_fault-0.1.2.dist-info/RECORD
