Metadata-Version: 2.1
Name: chaostoolkit-fault
Version: 0.1.2
Summary: Chaos Toolkit extension for the fault proxy
Author-Email: Sylvain Hellegouarch <sh@defuze.org>
License: Apache-2.0
Classifier: Development Status :: 5 - Production/Stable
Classifier: Intended Audience :: Developers
Classifier: License :: Freely Distributable
Classifier: License :: OSI Approved :: Apache Software License
Classifier: Operating System :: OS Independent
Classifier: Programming Language :: Python
Classifier: Programming Language :: Python :: 3
Classifier: Programming Language :: Python :: 3.10
Classifier: Programming Language :: Python :: 3.11
Classifier: Programming Language :: Python :: 3.12
Classifier: Programming Language :: Python :: 3.13
Classifier: Programming Language :: Python :: Implementation
Classifier: Programming Language :: Python :: Implementation :: CPython
Project-URL: documentation, https://chaostoolkit.org
Project-URL: repository, https://github.com/chaostoolkit-incubator/chaostoolkit-fault
Project-URL: changelog, https://github.com/chaostoolkit-incubator/chaostoolkit-fault/blob/master/CHANGELOG.md
Requires-Python: >=3.10
Requires-Dist: chaostoolkit-lib>=1.37
Requires-Dist: psutil>=7.0.0
